EC2S3Wrapper/EC2Manager.py
EC2S3Wrapper/S3Manager.py
EC2S3Wrapper/__init__.py
EC2S3Wrapper-1.0.2.dist-info/METADATA
EC2S3Wrapper-1.0.2.dist-info/WHEEL
EC2S3Wrapper-1.0.2.dist-info/top_level.txt
EC2S3Wrapper-1.0.2.dist-info/RECORD
