Metadata-Version: 2.1
Name: EC2S3Wrapper
Version: 1.0.2
Summary: EC2S3Wrapper is a Python package designed to simplify the management of AWS EC2 and S3 services. It provides an easy-to-use interface for common tasks like creating and managing EC2 instances, as well as uploading, downloading, and managing files in S3. Ideal for developers looking to streamline AWS operations with minimal code
Author: Suraj Yadav
Author-email: sam124.sy@gmail.com
Classifier: Programming Language :: Python :: 3
Classifier: Operating System :: OS Independent
Requires-Python: >=3.10
Requires-Dist: boto3
Requires-Dist: tabulate
